rishi_raj/utils.py
weather_rishiraj-1.0.0.0.dist-info/LICENSE
weather_rishiraj-1.0.0.0.dist-info/METADATA
weather_rishiraj-1.0.0.0.dist-info/WHEEL
weather_rishiraj-1.0.0.0.dist-info/entry_points.txt
weather_rishiraj-1.0.0.0.dist-info/top_level.txt
weather_rishiraj-1.0.0.0.dist-info/RECORD
