Metadata-Version: 2.1
Name: weather-rishiraj
Version: 1.0.0.0
Summary: A Python package to get weather reports for any location.
Home-page: https://github.com/wabrishi/pip
Author: Rishiraj
Author-email: rishiraj.python@gmail.com
License: MIT
Platform: UNKNOWN
Classifier: License :: OSI Approved :: MIT License
Classifier: Programming Language :: Python :: 3
Classifier: Programming Language :: Python :: 3.7
Requires-Dist: requests
